as_codegen/__init__.py
as_codegen/__main__.py
as_codegen/codegen.py
as_codegen/config.py
as_codegen/constants.py
as_codegen/exceptions.py
as_codegen/main.py
as_codegen/schema.py
as_codegen/settings.py
as_codegen/utils.py
as_codegen/client_generators/__init__.py
as_codegen/client_generators/arguments.py
as_codegen/client_generators/client.py
as_codegen/client_generators/comments.py
as_codegen/client_generators/constants.py
as_codegen/client_generators/custom_arguments.py
as_codegen/client_generators/custom_fields.py
as_codegen/client_generators/custom_fields_typing.py
as_codegen/client_generators/custom_generator_utils.py
as_codegen/client_generators/custom_operation.py
as_codegen/client_generators/enums.py
as_codegen/client_generators/fragments.py
as_codegen/client_generators/init_file.py
as_codegen/client_generators/input_fields.py
as_codegen/client_generators/input_types.py
as_codegen/client_generators/package.py
as_codegen/client_generators/result_fields.py
as_codegen/client_generators/result_types.py
as_codegen/client_generators/scalars.py
as_codegen/client_generators/types.py
as_codegen/client_generators/dependencies/__init__.py
as_codegen/client_generators/dependencies/async_base_client.py
as_codegen/client_generators/dependencies/async_base_client_open_telemetry.py
as_codegen/client_generators/dependencies/auth.py
as_codegen/client_generators/dependencies/base_client.py
as_codegen/client_generators/dependencies/base_client_open_telemetry.py
as_codegen/client_generators/dependencies/base_model.py
as_codegen/client_generators/dependencies/base_operation.py
as_codegen/client_generators/dependencies/config.py
as_codegen/client_generators/dependencies/exceptions.py
as_codegen/graphql_schema_generators/__init__.py
as_codegen/graphql_schema_generators/constants.py
as_codegen/graphql_schema_generators/directives.py
as_codegen/graphql_schema_generators/fields.py
as_codegen/graphql_schema_generators/named_types.py
as_codegen/graphql_schema_generators/schema.py
as_codegen-0.1.1.dist-info/METADATA
as_codegen-0.1.1.dist-info/WHEEL
as_codegen-0.1.1.dist-info/entry_points.txt
as_codegen-0.1.1.dist-info/licenses/LICENSE
as_codegen-0.1.1.dist-info/RECORD
